nin/__init__.py
nin/cli.py
nin/cli_dns.py
nin/nin.py
nin-0.1.0.dist-info/LICENSE
nin-0.1.0.dist-info/METADATA
nin-0.1.0.dist-info/WHEEL
nin-0.1.0.dist-info/entry_points.txt
nin-0.1.0.dist-info/top_level.txt
nin-0.1.0.dist-info/RECORD
