Metadata-Version: 2.1
Name: nin
Version: 0.1.0
Summary: network infos
Home-page: https://gitee.com/kin9-0rz/nin
Author: King Orz
Author-email: kin9-0rz@outlook.com
License: MIT license
Keywords: nin
Platform: UNKNOWN
Classifier: Development Status :: 2 - Pre-Alpha
Classifier: Intended Audience :: Developers
Classifier: License :: OSI Approved :: MIT License
Classifier: Natural Language :: English
Classifier: Programming Language :: Python :: 3
Classifier: Programming Language :: Python :: 3.5
Classifier: Programming Language :: Python :: 3.6
Classifier: Programming Language :: Python :: 3.7
Classifier: Programming Language :: Python :: 3.8
Requires-Python: >=3.5
License-File: LICENSE
Requires-Dist: Click (>=7.0)
Requires-Dist: dnspython
